zh/__init__.py
zh/search.py
sunone-0.1.0.dist-info/METADATA
sunone-0.1.0.dist-info/WHEEL
sunone-0.1.0.dist-info/top_level.txt
sunone-0.1.0.dist-info/zip-safe
sunone-0.1.0.dist-info/RECORD
