Metadata-Version: 2.1
Name: sunone
Version: 0.1.0
Summary: 这是一个测试包
Home-page: 
Author: yonghuiXu
Author-email: 2541128175@qq.com
Requires-Python: >=3.7
Requires-Dist: charset-normalizer (<4,>=2)
Requires-Dist: idna (<4,>=2.5)
Requires-Dist: urllib3 (<3,>=1.21.1)
Requires-Dist: certifi (>=2017.4.17)
